pygenprop/__init__.py
pygenprop/assign.py
pygenprop/assignment_database.py
pygenprop/assignment_file_parser.py
pygenprop/database_file_parser.py
pygenprop/database_reference.py
pygenprop/evidence.py
pygenprop/functional_element.py
pygenprop/genome_property.py
pygenprop/lib.py
pygenprop/literature_reference.py
pygenprop/results.py
pygenprop/step.py
pygenprop/tree.py
pygenprop-0.8.data/scripts/pygenprop
pygenprop-0.8.dist-info/LICENSE
pygenprop-0.8.dist-info/METADATA
pygenprop-0.8.dist-info/WHEEL
pygenprop-0.8.dist-info/top_level.txt
pygenprop-0.8.dist-info/zip-safe
pygenprop-0.8.dist-info/RECORD
