Metadata-Version: 2.1
Name: pygenprop
Version: 0.8
Summary: A python library for programmatic usage of EBI InterPro Genome Properties.
Home-page: https://github.com/Micromeda/pygenprop
Author: Lee Bergstrand
Author-email: lee.h.bergstrand@gmail.com
License: Apache License 2.0
Platform: UNKNOWN
Requires-Dist: numpy (>=1.13.3Cython>=0.29.13)
Requires-Dist: pandas (<1.0.0,>=0.25.0)
Requires-Dist: sqlalchemy (>=1.3.12)
Requires-Dist: scikit-bio (>=0.5.5)
